[
 {
   "APARTMENT_ID": 100016,
   "APARTMENT_TYPE_ID": 151776,
   "LANDLORD_ID": 387602247,
   "MONTHLY_RENT": 4551,
   "APARTMENT_NUMBER": 914,
   "APARTMENT_STREET_NAME": "Ronald Regan",
   "APARTMENT_CITY": "Youngstown",
   "APARTMENT_ZIPCODE": 96815,
   "TOTAL_AREA": 1500,
   "APARTMENT_STATUS": "Occupied"
 },
 {
   "APARTMENT_ID": 100047,
   "APARTMENT_TYPE_ID": 943594,
   "LANDLORD_ID": 197674876,
   "MONTHLY_RENT": 5339,
   "APARTMENT_NUMBER": 972,
   "APARTMENT_STREET_NAME": "Cambridge",
   "APARTMENT_CITY": "Shawnee Mission",
   "APARTMENT_ZIPCODE": 77505,
   "TOTAL_AREA": 2450,
   "APARTMENT_STATUS": "Occupied"
 },
 {
   "APARTMENT_ID": 100050,
   "APARTMENT_TYPE_ID": 948170,
   "LANDLORD_ID": 703939535,
   "MONTHLY_RENT": 2896,
   "APARTMENT_NUMBER": 7,
   "APARTMENT_STREET_NAME": "Daystar",
   "APARTMENT_CITY": "Springfield",
   "APARTMENT_ZIPCODE": 80255,
   "TOTAL_AREA": 3520,
   "APARTMENT_STATUS": "Occupied"
 },
 {
   "APARTMENT_ID": 100055,
   "APARTMENT_TYPE_ID": 351693,
   "LANDLORD_ID": 340551343,
   "MONTHLY_RENT": 5109,
   "APARTMENT_NUMBER": 2252,
   "APARTMENT_STREET_NAME": "Elgar",
   "APARTMENT_CITY": "Las Vegas",
   "APARTMENT_ZIPCODE": 85010,
   "TOTAL_AREA": 2400,
   "APARTMENT_STATUS": "Occupied"
 },
 {
   "APARTMENT_ID": 100067,
   "APARTMENT_TYPE_ID": 887919,
   "LANDLORD_ID": 688492234,
   "MONTHLY_RENT": 3439,
   "APARTMENT_NUMBER": 3600,
   "APARTMENT_STREET_NAME": "Bluestem",
   "APARTMENT_CITY": "Long Beach",
   "APARTMENT_ZIPCODE": 89135,
   "TOTAL_AREA": 1800,
   "APARTMENT_STATUS": "Vacant"
 },
 {
   "APARTMENT_ID": 100076,
   "APARTMENT_TYPE_ID": 743856,
   "LANDLORD_ID": 168057314,
   "MONTHLY_RENT": 4175,
   "APARTMENT_NUMBER": 57628,
   "APARTMENT_STREET_NAME": "Red Cloud",
   "APARTMENT_CITY": "Huntington Beach",
   "APARTMENT_ZIPCODE": 40205,
   "TOTAL_AREA": 1800,
   "APARTMENT_STATUS": "Occupied"
 },
 {
   "APARTMENT_ID": 100089,
   "APARTMENT_TYPE_ID": 317332,
   "LANDLORD_ID": 630313221,
   "MONTHLY_RENT": 5022,
   "APARTMENT_NUMBER": 94692,
   "APARTMENT_STREET_NAME": "Cordelia",
   "APARTMENT_CITY": "Salt Lake City",
   "APARTMENT_ZIPCODE": 93794,
   "TOTAL_AREA": 1800,
   "APARTMENT_STATUS": "Vacant"
 },
 {
   "APARTMENT_ID": 100094,
   "APARTMENT_TYPE_ID": 904633,
   "LANDLORD_ID": 466286531,
   "MONTHLY_RENT": 3654,
   "APARTMENT_NUMBER": 2635,
   "APARTMENT_STREET_NAME": "Golf View",
   "APARTMENT_CITY": "Roanoke",
   "APARTMENT_ZIPCODE": 23237,
   "TOTAL_AREA": 1500,
   "APARTMENT_STATUS": "Occupied"
 },
 {
   "APARTMENT_ID": 100109,
   "APARTMENT_TYPE_ID": 83226,
   "LANDLORD_ID": 619232134,
   "MONTHLY_RENT": 5926,
   "APARTMENT_NUMBER": 557,
   "APARTMENT_STREET_NAME": "Almo",
   "APARTMENT_CITY": "Watertown",
   "APARTMENT_ZIPCODE": 73179,
   "TOTAL_AREA": 3000,
   "APARTMENT_STATUS": "Occupied"
 },
 {
   "APARTMENT_ID": 100117,
   "APARTMENT_TYPE_ID": 153673,
   "LANDLORD_ID": 225970938,
   "MONTHLY_RENT": 4711,
   "APARTMENT_NUMBER": 12,
   "APARTMENT_STREET_NAME": "Kropf",
   "APARTMENT_CITY": "Springfield",
   "APARTMENT_ZIPCODE": 44185,
   "TOTAL_AREA": 3520,
   "APARTMENT_STATUS": "Occupied"
 },
 {
   "APARTMENT_ID": 100128,
   "APARTMENT_TYPE_ID": 687206,
   "LANDLORD_ID": 470973437,
   "MONTHLY_RENT": 5385,
   "APARTMENT_NUMBER": 4754,
   "APARTMENT_STREET_NAME": "Shopko",
   "APARTMENT_CITY": "Washington",
   "APARTMENT_ZIPCODE": 31217,
   "TOTAL_AREA": 1500,
   "APARTMENT_STATUS": "Occupied"
 },
 {
   "APARTMENT_ID": 100141,
   "APARTMENT_TYPE_ID": 367816,
   "LANDLORD_ID": 752161014,
   "MONTHLY_RENT": 5928,
   "APARTMENT_NUMBER": 225,
   "APARTMENT_STREET_NAME": "Blaine",
   "APARTMENT_CITY": "Huntington",
   "APARTMENT_ZIPCODE": 2305,
   "TOTAL_AREA": 1500,
   "APARTMENT_STATUS": "Occupied"
 },
 {
   "APARTMENT_ID": 100163,
   "APARTMENT_TYPE_ID": 754224,
   "LANDLORD_ID": 702414252,
   "MONTHLY_RENT": 4029,
   "APARTMENT_NUMBER": 5108,
   "APARTMENT_STREET_NAME": "Bonner",
   "APARTMENT_CITY": "San Antonio",
   "APARTMENT_ZIPCODE": 11355,
   "TOTAL_AREA": 3520,
   "APARTMENT_STATUS": "Occupied"
 },
 {
   "APARTMENT_ID": 100166,
   "APARTMENT_TYPE_ID": 315499,
   "LANDLORD_ID": 347362831,
   "MONTHLY_RENT": 4967,
   "APARTMENT_NUMBER": 10,
   "APARTMENT_STREET_NAME": "Mayer",
   "APARTMENT_CITY": "Washington",
   "APARTMENT_ZIPCODE": 37220,
   "TOTAL_AREA": 1800,
   "APARTMENT_STATUS": "Occupied"
 },
 {
   "APARTMENT_ID": 100180,
   "APARTMENT_TYPE_ID": 309075,
   "LANDLORD_ID": 213839298,
   "MONTHLY_RENT": 3834,
   "APARTMENT_NUMBER": 222,
   "APARTMENT_STREET_NAME": "Leroy",
   "APARTMENT_CITY": "Cincinnati",
   "APARTMENT_ZIPCODE": 33884,
   "TOTAL_AREA": 2450,
   "APARTMENT_STATUS": "Vacant"
 },
 {
   "APARTMENT_ID": 100197,
   "APARTMENT_TYPE_ID": 125933,
   "LANDLORD_ID": 796804276,
   "MONTHLY_RENT": 5055,
   "APARTMENT_NUMBER": 7098,
   "APARTMENT_STREET_NAME": "Bobwhite",
   "APARTMENT_CITY": "Fort Worth",
   "APARTMENT_ZIPCODE": 45454,
   "TOTAL_AREA": 2500,
   "APARTMENT_STATUS": "Vacant"
 },
 {
   "APARTMENT_ID": 100227,
   "APARTMENT_TYPE_ID": 869199,
   "LANDLORD_ID": 258963722,
   "MONTHLY_RENT": 5090,
   "APARTMENT_NUMBER": 3628,
   "APARTMENT_STREET_NAME": "Harbort",
   "APARTMENT_CITY": "Washington",
   "APARTMENT_ZIPCODE": 34282,
   "TOTAL_AREA": 2400,
   "APARTMENT_STATUS": "Occupied"
 },
 {
   "APARTMENT_ID": 100234,
   "APARTMENT_TYPE_ID": 668047,
   "LANDLORD_ID": 450116064,
   "MONTHLY_RENT": 3465,
   "APARTMENT_NUMBER": 95,
   "APARTMENT_STREET_NAME": "Eggendart",
   "APARTMENT_CITY": "Anaheim",
   "APARTMENT_ZIPCODE": 75074,
   "TOTAL_AREA": 3520,
   "APARTMENT_STATUS": "Vacant"
 },
 {
   "APARTMENT_ID": 100244,
   "APARTMENT_TYPE_ID": 984012,
   "LANDLORD_ID": 648583973,
   "MONTHLY_RENT": 3976,
   "APARTMENT_NUMBER": 735,
   "APARTMENT_STREET_NAME": "Cambridge",
   "APARTMENT_CITY": "Salt Lake City",
   "APARTMENT_ZIPCODE": 20851,
   "TOTAL_AREA": 3000,
   "APARTMENT_STATUS": "Vacant"
 },
 {
   "APARTMENT_ID": 100246,
   "APARTMENT_TYPE_ID": 557472,
   "LANDLORD_ID": 485904594,
   "MONTHLY_RENT": 2974,
   "APARTMENT_NUMBER": 3883,
   "APARTMENT_STREET_NAME": "Crowley",
   "APARTMENT_CITY": "Bismarck",
   "APARTMENT_ZIPCODE": 73124,
   "TOTAL_AREA": 3520,
   "APARTMENT_STATUS": "Vacant"
 },
 {
   "APARTMENT_ID": 100263,
   "APARTMENT_TYPE_ID": 591033,
   "LANDLORD_ID": 363330697,
   "MONTHLY_RENT": 4623,
   "APARTMENT_NUMBER": 939,
   "APARTMENT_STREET_NAME": "Shasta",
   "APARTMENT_CITY": "Merrifield",
   "APARTMENT_ZIPCODE": 33147,
   "TOTAL_AREA": 2400,
   "APARTMENT_STATUS": "Occupied"
 },
 {
   "APARTMENT_ID": 100264,
   "APARTMENT_TYPE_ID": 420898,
   "LANDLORD_ID": 663703329,
   "MONTHLY_RENT": 5655,
   "APARTMENT_NUMBER": 11621,
   "APARTMENT_STREET_NAME": "Arrowood",
   "APARTMENT_CITY": "Cincinnati",
   "APARTMENT_ZIPCODE": 35487,
   "TOTAL_AREA": 2400,
   "APARTMENT_STATUS": "Occupied"
 },
 {
   "APARTMENT_ID": 100277,
   "APARTMENT_TYPE_ID": 153171,
   "LANDLORD_ID": 649638434,
   "MONTHLY_RENT": 3127,
   "APARTMENT_NUMBER": 6,
   "APARTMENT_STREET_NAME": "Lyons",
   "APARTMENT_CITY": "Fort Wayne",
   "APARTMENT_ZIPCODE": 78291,
   "TOTAL_AREA": 2400,
   "APARTMENT_STATUS": "Vacant"
 },
 {
   "APARTMENT_ID": 100287,
   "APARTMENT_TYPE_ID": 632049,
   "LANDLORD_ID": 307528574,
   "MONTHLY_RENT": 5011,
   "APARTMENT_NUMBER": 755,
   "APARTMENT_STREET_NAME": "Hudson",
   "APARTMENT_CITY": "Newark",
   "APARTMENT_ZIPCODE": 89074,
   "TOTAL_AREA": 3520,
   "APARTMENT_STATUS": "Vacant"
 },
 {
   "APARTMENT_ID": 100296,
   "APARTMENT_TYPE_ID": 681891,
   "LANDLORD_ID": 532814810,
   "MONTHLY_RENT": 3792,
   "APARTMENT_NUMBER": 25,
   "APARTMENT_STREET_NAME": "Luster",
   "APARTMENT_CITY": "Milwaukee",
   "APARTMENT_ZIPCODE": 80044,
   "TOTAL_AREA": 3000,
   "APARTMENT_STATUS": "Vacant"
 },
 {
   "APARTMENT_ID": 100319,
   "APARTMENT_TYPE_ID": 610793,
   "LANDLORD_ID": 842537634,
   "MONTHLY_RENT": 4360,
   "APARTMENT_NUMBER": 52556,
   "APARTMENT_STREET_NAME": "Dennis",
   "APARTMENT_CITY": "Cleveland",
   "APARTMENT_ZIPCODE": 68105,
   "TOTAL_AREA": 3000,
   "APARTMENT_STATUS": "Vacant"
 },
 {
   "APARTMENT_ID": 100327,
   "APARTMENT_TYPE_ID": 817174,
   "LANDLORD_ID": 456586099,
   "MONTHLY_RENT": 4050,
   "APARTMENT_NUMBER": 0,
   "APARTMENT_STREET_NAME": "Coolidge",
   "APARTMENT_CITY": "Lexington",
   "APARTMENT_ZIPCODE": 23203,
   "TOTAL_AREA": 3520,
   "APARTMENT_STATUS": "Occupied"
 },
 {
   "APARTMENT_ID": 100331,
   "APARTMENT_TYPE_ID": 612152,
   "LANDLORD_ID": 418683533,
   "MONTHLY_RENT": 5260,
   "APARTMENT_NUMBER": 15,
   "APARTMENT_STREET_NAME": "Maple",
   "APARTMENT_CITY": "Brooklyn",
   "APARTMENT_ZIPCODE": 67230,
   "TOTAL_AREA": 1800,
   "APARTMENT_STATUS": "Vacant"
 },
 {
   "APARTMENT_ID": 100332,
   "APARTMENT_TYPE_ID": 328335,
   "LANDLORD_ID": 723933230,
   "MONTHLY_RENT": 3496,
   "APARTMENT_NUMBER": 596,
   "APARTMENT_STREET_NAME": "Dryden",
   "APARTMENT_CITY": "Valdosta",
   "APARTMENT_ZIPCODE": 24040,
   "TOTAL_AREA": 3000,
   "APARTMENT_STATUS": "Vacant"
 },
 {
   "APARTMENT_ID": 100348,
   "APARTMENT_TYPE_ID": 634398,
   "LANDLORD_ID": 101791286,
   "MONTHLY_RENT": 3903,
   "APARTMENT_NUMBER": 596,
   "APARTMENT_STREET_NAME": "Portage",
   "APARTMENT_CITY": "Miami",
   "APARTMENT_ZIPCODE": 92160,
   "TOTAL_AREA": 3520,
   "APARTMENT_STATUS": "Vacant"
 },
 {
   "APARTMENT_ID": 100352,
   "APARTMENT_TYPE_ID": 6139,
   "LANDLORD_ID": 390743251,
   "MONTHLY_RENT": 5211,
   "APARTMENT_NUMBER": 86,
   "APARTMENT_STREET_NAME": "Sauthoff",
   "APARTMENT_CITY": "Manchester",
   "APARTMENT_ZIPCODE": 72222,
   "TOTAL_AREA": 3000,
   "APARTMENT_STATUS": "Vacant"
 },
 {
   "APARTMENT_ID": 100367,
   "APARTMENT_TYPE_ID": 148283,
   "LANDLORD_ID": 467929392,
   "MONTHLY_RENT": 4347,
   "APARTMENT_NUMBER": 675,
   "APARTMENT_STREET_NAME": "Bay",
   "APARTMENT_CITY": "Stockton",
   "APARTMENT_ZIPCODE": 38181,
   "TOTAL_AREA": 1800,
   "APARTMENT_STATUS": "Occupied"
 },
 {
   "APARTMENT_ID": 100369,
   "APARTMENT_TYPE_ID": 693781,
   "LANDLORD_ID": 850572536,
   "MONTHLY_RENT": 3059,
   "APARTMENT_NUMBER": 181,
   "APARTMENT_STREET_NAME": "Northport",
   "APARTMENT_CITY": "Fort Worth",
   "APARTMENT_ZIPCODE": 14205,
   "TOTAL_AREA": 1800,
   "APARTMENT_STATUS": "Occupied"
 },
 {
   "APARTMENT_ID": 100370,
   "APARTMENT_TYPE_ID": 954151,
   "LANDLORD_ID": 566845651,
   "MONTHLY_RENT": 5295,
   "APARTMENT_NUMBER": 73852,
   "APARTMENT_STREET_NAME": "Spenser",
   "APARTMENT_CITY": "Hartford",
   "APARTMENT_ZIPCODE": 46825,
   "TOTAL_AREA": 1800,
   "APARTMENT_STATUS": "Vacant"
 },
 {
   "APARTMENT_ID": 100372,
   "APARTMENT_TYPE_ID": 506699,
   "LANDLORD_ID": 538169962,
   "MONTHLY_RENT": 2886,
   "APARTMENT_NUMBER": 5,
   "APARTMENT_STREET_NAME": "School",
   "APARTMENT_CITY": "New York City",
   "APARTMENT_ZIPCODE": 67230,
   "TOTAL_AREA": 3000,
   "APARTMENT_STATUS": "Occupied"
 },
 {
   "APARTMENT_ID": 100383,
   "APARTMENT_TYPE_ID": 722303,
   "LANDLORD_ID": 414303609,
   "MONTHLY_RENT": 2929,
   "APARTMENT_NUMBER": 7,
   "APARTMENT_STREET_NAME": "Cambridge",
   "APARTMENT_CITY": "Washington",
   "APARTMENT_ZIPCODE": 44710,
   "TOTAL_AREA": 3520,
   "APARTMENT_STATUS": "Occupied"
 },
 {
   "APARTMENT_ID": 100385,
   "APARTMENT_TYPE_ID": 689513,
   "LANDLORD_ID": 633498796,
   "MONTHLY_RENT": 5640,
   "APARTMENT_NUMBER": 66238,
   "APARTMENT_STREET_NAME": "Ridgeway",
   "APARTMENT_CITY": "Phoenix",
   "APARTMENT_ZIPCODE": 33355,
   "TOTAL_AREA": 1500,
   "APARTMENT_STATUS": "Occupied"
 },
 {
   "APARTMENT_ID": 100398,
   "APARTMENT_TYPE_ID": 710024,
   "LANDLORD_ID": 112319629,
   "MONTHLY_RENT": 5394,
   "APARTMENT_NUMBER": 672,
   "APARTMENT_STREET_NAME": "Straubel",
   "APARTMENT_CITY": "New Haven",
   "APARTMENT_ZIPCODE": 92612,
   "TOTAL_AREA": 3520,
   "APARTMENT_STATUS": "Vacant"
 },
 {
   "APARTMENT_ID": 100410,
   "APARTMENT_TYPE_ID": 437416,
   "LANDLORD_ID": 100255965,
   "MONTHLY_RENT": 5067,
   "APARTMENT_NUMBER": 87950,
   "APARTMENT_STREET_NAME": "Ramsey",
   "APARTMENT_CITY": "Charleston",
   "APARTMENT_ZIPCODE": 63143,
   "TOTAL_AREA": 2400,
   "APARTMENT_STATUS": "Occupied"
 },
 {
   "APARTMENT_ID": 100437,
   "APARTMENT_TYPE_ID": 105675,
   "LANDLORD_ID": 356036515,
   "MONTHLY_RENT": 3702,
   "APARTMENT_NUMBER": 3866,
   "APARTMENT_STREET_NAME": "Ilene",
   "APARTMENT_CITY": "Fort Pierce",
   "APARTMENT_ZIPCODE": 94913,
   "TOTAL_AREA": 3520,
   "APARTMENT_STATUS": "Vacant"
 },
 {
   "APARTMENT_ID": 100443,
   "APARTMENT_TYPE_ID": 372317,
   "LANDLORD_ID": 254391172,
   "MONTHLY_RENT": 4876,
   "APARTMENT_NUMBER": 40584,
   "APARTMENT_STREET_NAME": "Sutteridge",
   "APARTMENT_CITY": "Denver",
   "APARTMENT_ZIPCODE": 10203,
   "TOTAL_AREA": 3520,
   "APARTMENT_STATUS": "Vacant"
 },
 {
   "APARTMENT_ID": 100449,
   "APARTMENT_TYPE_ID": 505186,
   "LANDLORD_ID": 406847687,
   "MONTHLY_RENT": 3107,
   "APARTMENT_NUMBER": 90889,
   "APARTMENT_STREET_NAME": "Pawling",
   "APARTMENT_CITY": "Irvine",
   "APARTMENT_ZIPCODE": 37605,
   "TOTAL_AREA": 1800,
   "APARTMENT_STATUS": "Occupied"
 },
 {
   "APARTMENT_ID": 100456,
   "APARTMENT_TYPE_ID": 953,
   "LANDLORD_ID": 843704874,
   "MONTHLY_RENT": 4536,
   "APARTMENT_NUMBER": 6,
   "APARTMENT_STREET_NAME": "Grayhawk",
   "APARTMENT_CITY": "Saint Paul",
   "APARTMENT_ZIPCODE": 11205,
   "TOTAL_AREA": 3000,
   "APARTMENT_STATUS": "Vacant"
 },
 {
   "APARTMENT_ID": 100460,
   "APARTMENT_TYPE_ID": 843653,
   "LANDLORD_ID": 395446634,
   "MONTHLY_RENT": 2718,
   "APARTMENT_NUMBER": 8208,
   "APARTMENT_STREET_NAME": "Park Meadow",
   "APARTMENT_CITY": "Saint Joseph",
   "APARTMENT_ZIPCODE": 90045,
   "TOTAL_AREA": 2500,
   "APARTMENT_STATUS": "Vacant"
 },
 {
   "APARTMENT_ID": 100466,
   "APARTMENT_TYPE_ID": 703532,
   "LANDLORD_ID": 597139095,
   "MONTHLY_RENT": 5161,
   "APARTMENT_NUMBER": 2,
   "APARTMENT_STREET_NAME": "Onsgard",
   "APARTMENT_CITY": "Huntsville",
   "APARTMENT_ZIPCODE": 14683,
   "TOTAL_AREA": 1500,
   "APARTMENT_STATUS": "Occupied"
 },
 {
   "APARTMENT_ID": 100478,
   "APARTMENT_TYPE_ID": 118417,
   "LANDLORD_ID": 403362341,
   "MONTHLY_RENT": 5952,
   "APARTMENT_NUMBER": 28,
   "APARTMENT_STREET_NAME": "Fremont",
   "APARTMENT_CITY": "Warren",
   "APARTMENT_ZIPCODE": 33153,
   "TOTAL_AREA": 3000,
   "APARTMENT_STATUS": "Occupied"
 },
 {
   "APARTMENT_ID": 100485,
   "APARTMENT_TYPE_ID": 689658,
   "LANDLORD_ID": 555985317,
   "MONTHLY_RENT": 5394,
   "APARTMENT_NUMBER": 98065,
   "APARTMENT_STREET_NAME": "Menomonie",
   "APARTMENT_CITY": "Sacramento",
   "APARTMENT_ZIPCODE": 30316,
   "TOTAL_AREA": 3000,
   "APARTMENT_STATUS": "Vacant"
 },
 {
   "APARTMENT_ID": 100489,
   "APARTMENT_TYPE_ID": 552700,
   "LANDLORD_ID": 450036233,
   "MONTHLY_RENT": 3258,
   "APARTMENT_NUMBER": 73,
   "APARTMENT_STREET_NAME": "Butternut",
   "APARTMENT_CITY": "Kansas City",
   "APARTMENT_ZIPCODE": 18105,
   "TOTAL_AREA": 3000,
   "APARTMENT_STATUS": "Occupied"
 },
 {
   "APARTMENT_ID": 100491,
   "APARTMENT_TYPE_ID": 19762,
   "LANDLORD_ID": 429691784,
   "MONTHLY_RENT": 2634,
   "APARTMENT_NUMBER": 74846,
   "APARTMENT_STREET_NAME": "Morning",
   "APARTMENT_CITY": "Louisville",
   "APARTMENT_ZIPCODE": 96805,
   "TOTAL_AREA": 1500,
   "APARTMENT_STATUS": "Occupied"
 },
 {
   "APARTMENT_ID": 100505,
   "APARTMENT_TYPE_ID": 296848,
   "LANDLORD_ID": 510471486,
   "MONTHLY_RENT": 4079,
   "APARTMENT_NUMBER": 99370,
   "APARTMENT_STREET_NAME": "Hollow Ridge",
   "APARTMENT_CITY": "Denton",
   "APARTMENT_ZIPCODE": 89105,
   "TOTAL_AREA": 3520,
   "APARTMENT_STATUS": "Vacant"
 },
 {
   "APARTMENT_ID": 100513,
   "APARTMENT_TYPE_ID": 108791,
   "LANDLORD_ID": 303488091,
   "MONTHLY_RENT": 4376,
   "APARTMENT_NUMBER": 8,
   "APARTMENT_STREET_NAME": "Melody",
   "APARTMENT_CITY": "Richmond",
   "APARTMENT_ZIPCODE": 31296,
   "TOTAL_AREA": 2450,
   "APARTMENT_STATUS": "Occupied"
 },
 {
   "APARTMENT_ID": 100526,
   "APARTMENT_TYPE_ID": 161057,
   "LANDLORD_ID": 112458494,
   "MONTHLY_RENT": 2820,
   "APARTMENT_NUMBER": 372,
   "APARTMENT_STREET_NAME": "Forster",
   "APARTMENT_CITY": "Fresno",
   "APARTMENT_ZIPCODE": 45414,
   "TOTAL_AREA": 1800,
   "APARTMENT_STATUS": "Occupied"
 },
 {
   "APARTMENT_ID": 100537,
   "APARTMENT_TYPE_ID": 290282,
   "LANDLORD_ID": 789778493,
   "MONTHLY_RENT": 4378,
   "APARTMENT_NUMBER": 66,
   "APARTMENT_STREET_NAME": "Heffernan",
   "APARTMENT_CITY": "Lincoln",
   "APARTMENT_ZIPCODE": 23705,
   "TOTAL_AREA": 2400,
   "APARTMENT_STATUS": "Occupied"
 },
 {
   "APARTMENT_ID": 100540,
   "APARTMENT_TYPE_ID": 880377,
   "LANDLORD_ID": 801831869,
   "MONTHLY_RENT": 3141,
   "APARTMENT_NUMBER": 8,
   "APARTMENT_STREET_NAME": "Grim",
   "APARTMENT_CITY": "Baltimore",
   "APARTMENT_ZIPCODE": 40591,
   "TOTAL_AREA": 3520,
   "APARTMENT_STATUS": "Vacant"
 },
 {
   "APARTMENT_ID": 100569,
   "APARTMENT_TYPE_ID": 16188,
   "LANDLORD_ID": 518499165,
   "MONTHLY_RENT": 4151,
   "APARTMENT_NUMBER": 1,
   "APARTMENT_STREET_NAME": "Badeau",
   "APARTMENT_CITY": "Irvine",
   "APARTMENT_ZIPCODE": 37931,
   "TOTAL_AREA": 2400,
   "APARTMENT_STATUS": "Occupied"
 },
 {
   "APARTMENT_ID": 100571,
   "APARTMENT_TYPE_ID": 968645,
   "LANDLORD_ID": 327619378,
   "MONTHLY_RENT": 3649,
   "APARTMENT_NUMBER": 1,
   "APARTMENT_STREET_NAME": "Judy",
   "APARTMENT_CITY": "Fresno",
   "APARTMENT_ZIPCODE": 75037,
   "TOTAL_AREA": 2400,
   "APARTMENT_STATUS": "Vacant"
 },
 {
   "APARTMENT_ID": 100572,
   "APARTMENT_TYPE_ID": 48324,
   "LANDLORD_ID": 872653764,
   "MONTHLY_RENT": 3140,
   "APARTMENT_NUMBER": 46,
   "APARTMENT_STREET_NAME": "Menomonie",
   "APARTMENT_CITY": "Fresno",
   "APARTMENT_ZIPCODE": 12325,
   "TOTAL_AREA": 2400,
   "APARTMENT_STATUS": "Occupied"
 },
 {
   "APARTMENT_ID": 100584,
   "APARTMENT_TYPE_ID": 29748,
   "LANDLORD_ID": 343590462,
   "MONTHLY_RENT": 5106,
   "APARTMENT_NUMBER": 92,
   "APARTMENT_STREET_NAME": "Homewood",
   "APARTMENT_CITY": "Billings",
   "APARTMENT_ZIPCODE": 10170,
   "TOTAL_AREA": 1500,
   "APARTMENT_STATUS": "Occupied"
 },
 {
   "APARTMENT_ID": 100586,
   "APARTMENT_TYPE_ID": 70102,
   "LANDLORD_ID": 741749001,
   "MONTHLY_RENT": 4660,
   "APARTMENT_NUMBER": 42,
   "APARTMENT_STREET_NAME": "Farragut",
   "APARTMENT_CITY": "Kingsport",
   "APARTMENT_ZIPCODE": 75221,
   "TOTAL_AREA": 2400,
   "APARTMENT_STATUS": "Vacant"
 },
 {
   "APARTMENT_ID": 100606,
   "APARTMENT_TYPE_ID": 74791,
   "LANDLORD_ID": 464929892,
   "MONTHLY_RENT": 5773,
   "APARTMENT_NUMBER": 3734,
   "APARTMENT_STREET_NAME": "Rieder",
   "APARTMENT_CITY": "Manchester",
   "APARTMENT_ZIPCODE": 47719,
   "TOTAL_AREA": 3520,
   "APARTMENT_STATUS": "Occupied"
 },
 {
   "APARTMENT_ID": 100610,
   "APARTMENT_TYPE_ID": 455869,
   "LANDLORD_ID": 854253709,
   "MONTHLY_RENT": 5354,
   "APARTMENT_NUMBER": 6,
   "APARTMENT_STREET_NAME": "Lukken",
   "APARTMENT_CITY": "Toledo",
   "APARTMENT_ZIPCODE": 66606,
   "TOTAL_AREA": 3000,
   "APARTMENT_STATUS": "Vacant"
 },
 {
   "APARTMENT_ID": 100613,
   "APARTMENT_TYPE_ID": 904017,
   "LANDLORD_ID": 822673809,
   "MONTHLY_RENT": 4799,
   "APARTMENT_NUMBER": 29307,
   "APARTMENT_STREET_NAME": "John Wall",
   "APARTMENT_CITY": "San Diego",
   "APARTMENT_ZIPCODE": 33543,
   "TOTAL_AREA": 1500,
   "APARTMENT_STATUS": "Occupied"
 },
 {
   "APARTMENT_ID": 100629,
   "APARTMENT_TYPE_ID": 852221,
   "LANDLORD_ID": 123824099,
   "MONTHLY_RENT": 3135,
   "APARTMENT_NUMBER": 959,
   "APARTMENT_STREET_NAME": "Daystar",
   "APARTMENT_CITY": "Santa Barbara",
   "APARTMENT_ZIPCODE": 83206,
   "TOTAL_AREA": 1800,
   "APARTMENT_STATUS": "Vacant"
 },
 {
   "APARTMENT_ID": 100638,
   "APARTMENT_TYPE_ID": 514074,
   "LANDLORD_ID": 334104146,
   "MONTHLY_RENT": 3655,
   "APARTMENT_NUMBER": 151,
   "APARTMENT_STREET_NAME": "Sutteridge",
   "APARTMENT_CITY": "New Orleans",
   "APARTMENT_ZIPCODE": 78044,
   "TOTAL_AREA": 3520,
   "APARTMENT_STATUS": "Vacant"
 },
 {
   "APARTMENT_ID": 100644,
   "APARTMENT_TYPE_ID": 910408,
   "LANDLORD_ID": 438264009,
   "MONTHLY_RENT": 2519,
   "APARTMENT_NUMBER": 778,
   "APARTMENT_STREET_NAME": "Vahlen",
   "APARTMENT_CITY": "Laredo",
   "APARTMENT_ZIPCODE": 10131,
   "TOTAL_AREA": 1500,
   "APARTMENT_STATUS": "Occupied"
 },
 {
   "APARTMENT_ID": 100665,
   "APARTMENT_TYPE_ID": 999674,
   "LANDLORD_ID": 545027757,
   "MONTHLY_RENT": 3158,
   "APARTMENT_NUMBER": 916,
   "APARTMENT_STREET_NAME": "Mayer",
   "APARTMENT_CITY": "Des Moines",
   "APARTMENT_ZIPCODE": 6726,
   "TOTAL_AREA": 3000,
   "APARTMENT_STATUS": "Occupied"
 },
 {
   "APARTMENT_ID": 100668,
   "APARTMENT_TYPE_ID": 129606,
   "LANDLORD_ID": 799523347,
   "MONTHLY_RENT": 5355,
   "APARTMENT_NUMBER": 1222,
   "APARTMENT_STREET_NAME": "Schiller",
   "APARTMENT_CITY": "Denver",
   "APARTMENT_ZIPCODE": 77293,
   "TOTAL_AREA": 3000,
   "APARTMENT_STATUS": "Vacant"
 },
 {
   "APARTMENT_ID": 100669,
   "APARTMENT_TYPE_ID": 125640,
   "LANDLORD_ID": 612760767,
   "MONTHLY_RENT": 2814,
   "APARTMENT_NUMBER": 8,
   "APARTMENT_STREET_NAME": "Moulton",
   "APARTMENT_CITY": "Denver",
   "APARTMENT_ZIPCODE": 25362,
   "TOTAL_AREA": 2400,
   "APARTMENT_STATUS": "Occupied"
 },
 {
   "APARTMENT_ID": 100676,
   "APARTMENT_TYPE_ID": 456564,
   "LANDLORD_ID": 247781107,
   "MONTHLY_RENT": 4904,
   "APARTMENT_NUMBER": 9,
   "APARTMENT_STREET_NAME": "Knutson",
   "APARTMENT_CITY": "San Antonio",
   "APARTMENT_ZIPCODE": 98411,
   "TOTAL_AREA": 1500,
   "APARTMENT_STATUS": "Occupied"
 },
 {
   "APARTMENT_ID": 100677,
   "APARTMENT_TYPE_ID": 460506,
   "LANDLORD_ID": 662220203,
   "MONTHLY_RENT": 5512,
   "APARTMENT_NUMBER": 961,
   "APARTMENT_STREET_NAME": "Dennis",
   "APARTMENT_CITY": "Las Vegas",
   "APARTMENT_ZIPCODE": 17105,
   "TOTAL_AREA": 2450,
   "APARTMENT_STATUS": "Occupied"
 },
 {
   "APARTMENT_ID": 100689,
   "APARTMENT_TYPE_ID": 232633,
   "LANDLORD_ID": 443757095,
   "MONTHLY_RENT": 5280,
   "APARTMENT_NUMBER": 968,
   "APARTMENT_STREET_NAME": "Redwing",
   "APARTMENT_CITY": "Lincoln",
   "APARTMENT_ZIPCODE": 14905,
   "TOTAL_AREA": 1800,
   "APARTMENT_STATUS": "Vacant"
 },
 {
   "APARTMENT_ID": 100706,
   "APARTMENT_TYPE_ID": 169392,
   "LANDLORD_ID": 314838746,
   "MONTHLY_RENT": 3195,
   "APARTMENT_NUMBER": 4574,
   "APARTMENT_STREET_NAME": "Bunker Hill",
   "APARTMENT_CITY": "Lexington",
   "APARTMENT_ZIPCODE": 39705,
   "TOTAL_AREA": 3520,
   "APARTMENT_STATUS": "Occupied"
 },
 {
   "APARTMENT_ID": 100723,
   "APARTMENT_TYPE_ID": 366989,
   "LANDLORD_ID": 537658308,
   "MONTHLY_RENT": 2955,
   "APARTMENT_NUMBER": 368,
   "APARTMENT_STREET_NAME": "Del Mar",
   "APARTMENT_CITY": "Washington",
   "APARTMENT_ZIPCODE": 91328,
   "TOTAL_AREA": 2450,
   "APARTMENT_STATUS": "Vacant"
 },
 {
   "APARTMENT_ID": 100755,
   "APARTMENT_TYPE_ID": 519675,
   "LANDLORD_ID": 402114347,
   "MONTHLY_RENT": 3373,
   "APARTMENT_NUMBER": 5816,
   "APARTMENT_STREET_NAME": "Manufacturers",
   "APARTMENT_CITY": "Salem",
   "APARTMENT_ZIPCODE": 27658,
   "TOTAL_AREA": 2400,
   "APARTMENT_STATUS": "Vacant"
 },
 {
   "APARTMENT_ID": 100772,
   "APARTMENT_TYPE_ID": 634434,
   "LANDLORD_ID": 277069732,
   "MONTHLY_RENT": 5700,
   "APARTMENT_NUMBER": 3,
   "APARTMENT_STREET_NAME": "Sloan",
   "APARTMENT_CITY": "Honolulu",
   "APARTMENT_ZIPCODE": 24024,
   "TOTAL_AREA": 2500,
   "APARTMENT_STATUS": "Vacant"
 },
 {
   "APARTMENT_ID": 100777,
   "APARTMENT_TYPE_ID": 539734,
   "LANDLORD_ID": 193177672,
   "MONTHLY_RENT": 3639,
   "APARTMENT_NUMBER": 16,
   "APARTMENT_STREET_NAME": "Harper",
   "APARTMENT_CITY": "Lexington",
   "APARTMENT_ZIPCODE": 37250,
   "TOTAL_AREA": 2450,
   "APARTMENT_STATUS": "Vacant"
 },
 {
   "APARTMENT_ID": 100794,
   "APARTMENT_TYPE_ID": 680040,
   "LANDLORD_ID": 328725848,
   "MONTHLY_RENT": 5685,
   "APARTMENT_NUMBER": 31,
   "APARTMENT_STREET_NAME": "Tennessee",
   "APARTMENT_CITY": "Washington",
   "APARTMENT_ZIPCODE": 63143,
   "TOTAL_AREA": 3000,
   "APARTMENT_STATUS": "Vacant"
 },
 {
   "APARTMENT_ID": 100800,
   "APARTMENT_TYPE_ID": 330745,
   "LANDLORD_ID": 607886351,
   "MONTHLY_RENT": 3489,
   "APARTMENT_NUMBER": 28,
   "APARTMENT_STREET_NAME": "Cherokee",
   "APARTMENT_CITY": "Indianapolis",
   "APARTMENT_ZIPCODE": 80920,
   "TOTAL_AREA": 2450,
   "APARTMENT_STATUS": "Occupied"
 },
 {
   "APARTMENT_ID": 100808,
   "APARTMENT_TYPE_ID": 979679,
   "LANDLORD_ID": 786107330,
   "MONTHLY_RENT": 5996,
   "APARTMENT_NUMBER": 1038,
   "APARTMENT_STREET_NAME": "Sutherland",
   "APARTMENT_CITY": "Wichita",
   "APARTMENT_ZIPCODE": 60158,
   "TOTAL_AREA": 3520,
   "APARTMENT_STATUS": "Vacant"
 },
 {
   "APARTMENT_ID": 100818,
   "APARTMENT_TYPE_ID": 806336,
   "LANDLORD_ID": 640704326,
   "MONTHLY_RENT": 5272,
   "APARTMENT_NUMBER": 8,
   "APARTMENT_STREET_NAME": "Pennsylvania",
   "APARTMENT_CITY": "Portsmouth",
   "APARTMENT_ZIPCODE": 11254,
   "TOTAL_AREA": 2500,
   "APARTMENT_STATUS": "Vacant"
 },
 {
   "APARTMENT_ID": 100820,
   "APARTMENT_TYPE_ID": 457905,
   "LANDLORD_ID": 621226997,
   "MONTHLY_RENT": 4656,
   "APARTMENT_NUMBER": 0,
   "APARTMENT_STREET_NAME": "Eastlawn",
   "APARTMENT_CITY": "Arlington",
   "APARTMENT_ZIPCODE": 47134,
   "TOTAL_AREA": 3520,
   "APARTMENT_STATUS": "Vacant"
 },
 {
   "APARTMENT_ID": 100839,
   "APARTMENT_TYPE_ID": 611190,
   "LANDLORD_ID": 760793279,
   "MONTHLY_RENT": 4887,
   "APARTMENT_NUMBER": 2136,
   "APARTMENT_STREET_NAME": "Fallview",
   "APARTMENT_CITY": "Shawnee Mission",
   "APARTMENT_ZIPCODE": 28055,
   "TOTAL_AREA": 1500,
   "APARTMENT_STATUS": "Occupied"
 },
 {
   "APARTMENT_ID": 100846,
   "APARTMENT_TYPE_ID": 310650,
   "LANDLORD_ID": 491696637,
   "MONTHLY_RENT": 3756,
   "APARTMENT_NUMBER": 1,
   "APARTMENT_STREET_NAME": "Stone Corner",
   "APARTMENT_CITY": "Midland",
   "APARTMENT_ZIPCODE": 84145,
   "TOTAL_AREA": 2400,
   "APARTMENT_STATUS": "Vacant"
 },
 {
   "APARTMENT_ID": 100847,
   "APARTMENT_TYPE_ID": 510875,
   "LANDLORD_ID": 659108716,
   "MONTHLY_RENT": 2576,
   "APARTMENT_NUMBER": 7,
   "APARTMENT_STREET_NAME": "Myrtle",
   "APARTMENT_CITY": "Wichita",
   "APARTMENT_ZIPCODE": 29215,
   "TOTAL_AREA": 3000,
   "APARTMENT_STATUS": "Vacant"
 },
 {
   "APARTMENT_ID": 100850,
   "APARTMENT_TYPE_ID": 628498,
   "LANDLORD_ID": 174481315,
   "MONTHLY_RENT": 5445,
   "APARTMENT_NUMBER": 990,
   "APARTMENT_STREET_NAME": "Westend",
   "APARTMENT_CITY": "Tulsa",
   "APARTMENT_ZIPCODE": 29411,
   "TOTAL_AREA": 2450,
   "APARTMENT_STATUS": "Occupied"
 },
 {
   "APARTMENT_ID": 100864,
   "APARTMENT_TYPE_ID": 747472,
   "LANDLORD_ID": 636370788,
   "MONTHLY_RENT": 4493,
   "APARTMENT_NUMBER": 68051,
   "APARTMENT_STREET_NAME": "Eagan",
   "APARTMENT_CITY": "Columbus",
   "APARTMENT_ZIPCODE": 53215,
   "TOTAL_AREA": 3000,
   "APARTMENT_STATUS": "Occupied"
 },
 {
   "APARTMENT_ID": 100876,
   "APARTMENT_TYPE_ID": 714645,
   "LANDLORD_ID": 632251572,
   "MONTHLY_RENT": 3238,
   "APARTMENT_NUMBER": 1,
   "APARTMENT_STREET_NAME": "Gerald",
   "APARTMENT_CITY": "Washington",
   "APARTMENT_ZIPCODE": 90081,
   "TOTAL_AREA": 3000,
   "APARTMENT_STATUS": "Occupied"
 },
 {
   "APARTMENT_ID": 100877,
   "APARTMENT_TYPE_ID": 693685,
   "LANDLORD_ID": 505037401,
   "MONTHLY_RENT": 5584,
   "APARTMENT_NUMBER": 57526,
   "APARTMENT_STREET_NAME": "Carioca",
   "APARTMENT_CITY": "Erie",
   "APARTMENT_ZIPCODE": 90605,
   "TOTAL_AREA": 1500,
   "APARTMENT_STATUS": "Occupied"
 },
 {
   "APARTMENT_ID": 100878,
   "APARTMENT_TYPE_ID": 688327,
   "LANDLORD_ID": 133141493,
   "MONTHLY_RENT": 2877,
   "APARTMENT_NUMBER": 7305,
   "APARTMENT_STREET_NAME": "Gateway",
   "APARTMENT_CITY": "Florence",
   "APARTMENT_ZIPCODE": 92835,
   "TOTAL_AREA": 1500,
   "APARTMENT_STATUS": "Vacant"
 },
 {
   "APARTMENT_ID": 100943,
   "APARTMENT_TYPE_ID": 989571,
   "LANDLORD_ID": 185646716,
   "MONTHLY_RENT": 4453,
   "APARTMENT_NUMBER": 730,
   "APARTMENT_STREET_NAME": "Chinook",
   "APARTMENT_CITY": "Fresno",
   "APARTMENT_ZIPCODE": 98185,
   "TOTAL_AREA": 3520,
   "APARTMENT_STATUS": "Vacant"
 },
 {
   "APARTMENT_ID": 100975,
   "APARTMENT_TYPE_ID": 827932,
   "LANDLORD_ID": 113156367,
   "MONTHLY_RENT": 3835,
   "APARTMENT_NUMBER": 227,
   "APARTMENT_STREET_NAME": "Dexter",
   "APARTMENT_CITY": "Melbourne",
   "APARTMENT_ZIPCODE": 49505,
   "TOTAL_AREA": 1800,
   "APARTMENT_STATUS": "Vacant"
 },
 {
   "APARTMENT_ID": 100979,
   "APARTMENT_TYPE_ID": 218719,
   "LANDLORD_ID": 126338248,
   "MONTHLY_RENT": 4166,
   "APARTMENT_NUMBER": 969,
   "APARTMENT_STREET_NAME": "Marcy",
   "APARTMENT_CITY": "Pompano Beach",
   "APARTMENT_ZIPCODE": 92030,
   "TOTAL_AREA": 1800,
   "APARTMENT_STATUS": "Occupied"
 },
 {
   "APARTMENT_ID": 100985,
   "APARTMENT_TYPE_ID": 113629,
   "LANDLORD_ID": 257277578,
   "MONTHLY_RENT": 5403,
   "APARTMENT_NUMBER": 182,
   "APARTMENT_STREET_NAME": "Rockefeller",
   "APARTMENT_CITY": "Jamaica",
   "APARTMENT_ZIPCODE": 10464,
   "TOTAL_AREA": 2400,
   "APARTMENT_STATUS": "Vacant"
 },
 {
   "APARTMENT_ID": 100987,
   "APARTMENT_TYPE_ID": 775237,
   "LANDLORD_ID": 758040959,
   "MONTHLY_RENT": 4289,
   "APARTMENT_NUMBER": 3,
   "APARTMENT_STREET_NAME": "Ryan",
   "APARTMENT_CITY": "Evansville",
   "APARTMENT_ZIPCODE": 37605,
   "TOTAL_AREA": 2450,
   "APARTMENT_STATUS": "Vacant"
 },
 {
   "APARTMENT_ID": 100990,
   "APARTMENT_TYPE_ID": 575886,
   "LANDLORD_ID": 792588741,
   "MONTHLY_RENT": 2888,
   "APARTMENT_NUMBER": 296,
   "APARTMENT_STREET_NAME": "Del Sol",
   "APARTMENT_CITY": "Santa Barbara",
   "APARTMENT_ZIPCODE": 90025,
   "TOTAL_AREA": 2400,
   "APARTMENT_STATUS": "Vacant"
 },
 {
   "APARTMENT_ID": 100993,
   "APARTMENT_TYPE_ID": 36259,
   "LANDLORD_ID": 108728299,
   "MONTHLY_RENT": 5645,
   "APARTMENT_NUMBER": 0,
   "APARTMENT_STREET_NAME": "Eastwood",
   "APARTMENT_CITY": "Fullerton",
   "APARTMENT_ZIPCODE": 23504,
   "TOTAL_AREA": 2450,
   "APARTMENT_STATUS": "Vacant"
 }
]